liso/__init__.py
liso/config.py
liso/covariable.py
liso/elements.py
liso/exceptions.py
liso/logging.py
liso/utils.py
liso/experiment/__init__.py
liso/experiment/doocs_app.py
liso/experiment/doocs_channels.py
liso/experiment/doocs_interface.py
liso/experiment/machine_interface.py
liso/experiment/tests/__init__.py
liso/experiment/tests/test_doocs_app.py
liso/experiment/tests/test_doocs_channels.py
liso/experiment/tests/test_doocs_interface.py
liso/io/__init__.py
liso/io/channel_data.py
liso/io/file_access.py
liso/io/reader.py
liso/io/tempdir.py
liso/io/writer.py
liso/io/tests/__init__.py
liso/io/tests/test_fileaccess.py
liso/io/tests/test_reader.py
liso/io/tests/test_tempdir.py
liso/io/tests/test_writer.py
liso/optimization/__init__.py
liso/optimization/constraint.py
liso/optimization/linac_optimization.py
liso/optimization/objective.py
liso/optimization/opt_utils.py
liso/optimization/variable.py
liso/optimization/tests/__init__.py
liso/optimizers/__init__.py
liso/optimizers/alpso.py
liso/optimizers/nelder_mead.py
liso/optimizers/optimizer.py
liso/optimizers/pyALPSO.py
liso/optimizers/pyNelderMead.py
liso/optimizers/pySDPEN.py
liso/optimizers/pyopt_optimizer.py
liso/optimizers/tests/__init__.py
liso/optimizers/tests/opt_problems.py
liso/optimizers/tests/test_alpso.py
liso/optimizers/tests/test_nelderMead.py
liso/optimizers/tests/test_sdpen.py
liso/proc/__init__.py
liso/proc/beam_parameters.py
liso/proc/line_analysis.py
liso/proc/line_parameters.py
liso/proc/line_parser.py
liso/proc/phasespace.py
liso/proc/phasespace_analysis.py
liso/proc/phasespace_parser.py
liso/proc/proc_utils.py
liso/proc/tests/__init__.py
liso/proc/tests/test_line.py
liso/proc/tests/test_phasespace.py
liso/proc/tests/test_phasespace_analysis.py
liso/scan/__init__.py
liso/scan/abstract_scan.py
liso/scan/linac_scan.py
liso/scan/machine_scan.py
liso/scan/scan_param.py
liso/scan/tests/__init__.py
liso/scan/tests/test_linacscan.py
liso/scan/tests/test_machinescan.py
liso/scan/tests/test_scanparam.py
liso-0.5.0.dist-info/LICENSE
liso-0.5.0.dist-info/METADATA
liso-0.5.0.dist-info/WHEEL
liso-0.5.0.dist-info/entry_points.txt
liso-0.5.0.dist-info/top_level.txt
liso-0.5.0.dist-info/RECORD
