Metadata-Version: 2.1
Name: liso
Version: 0.5.0
Summary: Python API for LInac Simulation and Optimization
Home-page: https://github.com/zhujun98/liso
Author: Jun Zhu
Author-email: zhujun981661@gmail.com
License: UNKNOWN
Download-URL: https://github.com/zhujun98/liso
Platform: UNKNOWN
Classifier: Development Status :: 4 - Beta
Classifier: Intended Audience :: Science/Research
Classifier: License :: OSI Approved :: GNU General Public License v3 (GPLv3)
Classifier: Operating System :: POSIX :: Linux
Classifier: Operating System :: MacOS
Classifier: Programming Language :: Python :: 3.7
Classifier: Programming Language :: Python :: 3.8
Classifier: Programming Language :: Python :: 3.9
Classifier: Topic :: Scientific/Engineering :: Artificial Intelligence
Classifier: Topic :: Scientific/Engineering :: Information Analysis
Classifier: Topic :: Scientific/Engineering :: Physics
Requires-Python: >=3.7
License-File: LICENSE
Requires-Dist: numpy (>=1.18)
Requires-Dist: pandas (>=1.1)
Requires-Dist: scipy (>=1.4.1)
Requires-Dist: h5py (>=2.10)
Requires-Dist: matplotlib
Requires-Dist: pydantic (>=1.7.2)
Requires-Dist: sortedcontainers (>=2.4)
Provides-Extra: test
Requires-Dist: pytest ; extra == 'test'
Requires-Dist: pylint ; extra == 'test'
